pytest_vimqf/__init__.py
pytest_vimqf/main.py
pytest_vimqf-0.8.1.dist-info/entry_points.txt
pytest_vimqf-0.8.1.dist-info/LICENSE
pytest_vimqf-0.8.1.dist-info/WHEEL
pytest_vimqf-0.8.1.dist-info/METADATA
pytest_vimqf-0.8.1.dist-info/RECORD
