Metadata-Version: 2.1
Name: pytest-vimqf
Version: 0.8.1
Summary: A simple pytest plugin that will shrink pytest output when specified, to fit vim quickfix window.
Home-page: https://github.com/CarloDePieri/pytest_vimqf
License: GPL-3.0-only
Keywords: pytest,vim
Author: Carlo De Pieri
Requires-Python: >=3.6,<4.0
Classifier: Development Status :: 4 - Beta
Classifier: Framework :: Pytest
Classifier: Intended Audience :: Developers
Classifier: License :: OSI Approved :: GNU General Public License v3 (GPLv3)
Classifier: Programming Language :: Python :: 3
Classifier: Programming Language :: Python :: 3.6
Classifier: Programming Language :: Python :: 3.7
Classifier: Programming Language :: Python :: 3.8
Classifier: Programming Language :: Python :: 3.9
Classifier: Topic :: Software Development :: Libraries
Classifier: Topic :: Software Development :: Testing
Classifier: Topic :: Utilities
Requires-Dist: pytest (>=6.2.2,<7.0.0)
Project-URL: Repository, https://github.com/CarloDePieri/pytest_vimqf
